monkeybox/__init__.py
monkeybox/py.typed
monkeybox/core/__init__.py
monkeybox/core/agent.py
monkeybox/core/anthropic_model.py
monkeybox/core/base_model.py
monkeybox/core/exceptions.py
monkeybox/core/logger.py
monkeybox/core/mcp_client.py
monkeybox/core/openai_model.py
monkeybox/core/tools.py
monkeybox-0.1.0.dist-info/METADATA
monkeybox-0.1.0.dist-info/WHEEL
monkeybox-0.1.0.dist-info/licenses/LICENSE
monkeybox-0.1.0.dist-info/RECORD
