Metadata-Version: 2.4
Name: monkeybox
Version: 0.1.0
Summary: A minimal, observable agent framework for building AI agents with OpenAI and Anthropic
Project-URL: Homepage, https://github.com/Chen-Oliver/monkeybox
Project-URL: Repository, https://github.com/Chen-Oliver/monkeybox
Project-URL: Documentation, https://github.com/Chen-Oliver/monkeybox/tree/main/docs
Project-URL: Bug Tracker, https://github.com/Chen-Oliver/monkeybox/issues
Author: Oliver Chen
License: MIT
License-File: LICENSE
Keywords: agents,ai,anthropic,async,claude,framework,gpt,llm,mcp,openai
Classifier: Development Status :: 4 - Beta
Classifier: Framework :: AsyncIO
Classifier: Intended Audience :: Developers
Classifier: License :: OSI Approved :: MIT License
Classifier: Programming Language :: Python :: 3
Classifier: Programming Language :: Python :: 3.11
Classifier: Programming Language :: Python :: 3.12
Classifier: Programming Language :: Python :: 3.13
Classifier: Topic :: Scientific/Engineering :: Artificial Intelligence
Classifier: Topic :: Software Development :: Libraries :: Python Modules
Classifier: Typing :: Typed
Requires-Python: >=3.11
Requires-Dist: anthropic>=0.39.0
Requires-Dist: mcp>=1.0.0
Requires-Dist: numpydoc>=1.9.0
Requires-Dist: openai>=1.0.0
Requires-Dist: pydantic>=2.11.7
Requires-Dist: python-dotenv>=1.1.1
Requires-Dist: rich>=14.0.0
Requires-Dist: tenacity>=9.0.0
Requires-Dist: weave>=0.51.59
Provides-Extra: web
Requires-Dist: fastapi>=0.100.0; extra == 'web'
Requires-Dist: uvicorn[standard]>=0.23.0; extra == 'web'
